playwright_analyzer/__init__.py
playwright_analyzer/agent.py
playwright_analyzer/analyze_report.py
playwright_analyzer/report_injector.py
playwright_analyzer/report_parser.py
playwright_analyzer-0.1.2.dist-info/METADATA
playwright_analyzer-0.1.2.dist-info/WHEEL
playwright_analyzer-0.1.2.dist-info/entry_points.txt
playwright_analyzer-0.1.2.dist-info/licenses/LICENSE
playwright_analyzer-0.1.2.dist-info/RECORD
