Metadata-Version: 2.4
Name: playwright-analyzer
Version: 0.1.2
Summary: AI-powered Playwright test report analyzer using PydanticAI
Author-email: Your Name <ramchiyan1093@gmail.com>
License: MIT
License-File: LICENSE
Keywords: ai,analysis,playwright,test-reports,testing
Classifier: Development Status :: 4 - Beta
Classifier: Intended Audience :: Developers
Classifier: License :: OSI Approved :: MIT License
Classifier: Programming Language :: Python :: 3
Classifier: Programming Language :: Python :: 3.9
Classifier: Programming Language :: Python :: 3.10
Classifier: Programming Language :: Python :: 3.11
Classifier: Programming Language :: Python :: 3.12
Classifier: Topic :: Software Development :: Testing
Requires-Python: >=3.9
Requires-Dist: aiofiles>=24.0.0
Requires-Dist: beautifulsoup4>=4.12.0
Requires-Dist: jinja2>=3.1.0
Requires-Dist: lxml>=4.9.0
Requires-Dist: openai>=1.0.0
Requires-Dist: pydantic-ai>=0.0.16
Requires-Dist: pydantic>=2.0.0
Requires-Dist: python-dotenv>=1.0.0
Requires-Dist: rich>=13.0.0
Provides-Extra: dev
Requires-Dist: black>=23.0.0; extra == 'dev'
Requires-Dist: mypy>=1.0.0; extra == 'dev'
Requires-Dist: pre-commit>=3.3.0; extra == 'dev'
Requires-Dist: pytest-asyncio>=0.21.0; extra == 'dev'
Requires-Dist: pytest-cov>=4.1.0; extra == 'dev'
Requires-Dist: pytest>=7.0.0; extra == 'dev'
Requires-Dist: ruff>=0.1.0; extra == 'dev'
Provides-Extra: docs
Requires-Dist: mkdocs-material>=9.0.0; extra == 'docs'
Requires-Dist: mkdocs>=1.5.0; extra == 'docs'
Requires-Dist: mkdocstrings[python]>=0.22.0; extra == 'docs'
